seedme
