Metadata-Version: 1.1
Name: seedme
Version: 0.9.8
Summary: Python REST client for SeedMe.org
Home-page: https://www.seedme.org/downloads
Author: Amit Chourasia
Author-email: UNKNOWN
License: Copyright (c) The Regents of the University of California, 2015
